{
    "header": {
        "suburb": "Birchgrove",
        "state": "NSW",
        "propertyCategory": "House"
    },
    "series": {
        "seriesInfo": [
            {
                "year": 2011,
                "month": 9,
                "values": {
                    "medianSoldPrice": 1160000,
                    "numberSold": 16,
                    "highestSoldPrice": 3200000,
                    "lowestSoldPrice": 650000,
                    "5thPercentileSoldPrice": 650000,
                    "25thPercentileSoldPrice": 860000,
                    "75thPercentileSoldPrice": 1812000,
                    "95thPercentileSoldPrice": 3200000,
                    "medianSaleListingPrice": 1325000,
                    "numberSaleListing": 38,
                    "highestSaleListingPrice": 5000000,
                    "lowestSaleListingPrice": 650000,
                    "auctionNumberAuctioned": 12,
                    "auctionNumberSold": 4,
                    "auctionNumberWithdrawn": null,
                    "daysOnMarket": 140,
                    "discountPercentage": null,
                    "medianRentListingPrice": 838,
                    "numberRentListing": 38,
                    "highestRentListingPrice": 2850,
                    "lowestRentListingPrice": 500
                }
            },
            {
                "year": 2011,
                "month": 12,
                "values": {
                    "medianSoldPrice": 1611000,
                    "numberSold": 17,
                    "highestSoldPrice": 4550000,
                    "lowestSoldPrice": 650000,
                    "5thPercentileSoldPrice": 650000,
                    "25thPercentileSoldPrice": 950000,
                    "75thPercentileSoldPrice": 1985000,
                    "95thPercentileSoldPrice": 4550000,
                    "medianSaleListingPrice": 1615000,
                    "numberSaleListing": 33,
                    "highestSaleListingPrice": 4950000,
                    "lowestSaleListingPrice": 675000,
                    "auctionNumberAuctioned": 9,
                    "auctionNumberSold": 2,
                    "auctionNumberWithdrawn": null,
                    "daysOnMarket": 78,
                    "discountPercentage": null,
                    "medianRentListingPrice": 825,
                    "numberRentListing": 25,
                    "highestRentListingPrice": 2500,
                    "lowestRentListingPrice": 480
                }
            },
            {
                "year": 2012,
                "month": 3,
                "values": {
                    "medianSoldPrice": 1100000,
                    "numberSold": 11,
                    "highestSoldPrice": 3050000,
                    "lowestSoldPrice": 804000,
                    "5thPercentileSoldPrice": 804000,
                    "25thPercentileSoldPrice": 1035000,
                    "75thPercentileSoldPrice": 1650000,
                    "95thPercentileSoldPrice": 3050000,
                    "medianSaleListingPrice": 1329000,
                    "numberSaleListing": 28,
                    "highestSaleListingPrice": 5500000,
                    "lowestSaleListingPrice": 795000,
                    "auctionNumberAuctioned": 8,
                    "auctionNumberSold": 2,
                    "auctionNumberWithdrawn": null,
                    "daysOnMarket": null,
                    "discountPercentage": null,
                    "medianRentListingPrice": 850,
                    "numberRentListing": 29,
                    "highestRentListingPrice": 2200,
                    "lowestRentListingPrice": 420
                }
            },
            {
                "year": 2012,
                "month": 6,
                "values": {
                    "medianSoldPrice": 1150000,
                    "numberSold": 14,
                    "highestSoldPrice": 4050000,
                    "lowestSoldPrice": 710000,
                    "5thPercentileSoldPrice": 710000,
                    "25thPercentileSoldPrice": 926000,
                    "75thPercentileSoldPrice": 1800000,
                    "95thPercentileSoldPrice": 4050000,
                    "medianSaleListingPrice": 1275000,
                    "numberSaleListing": 28,
                    "highestSaleListingPrice": 5500000,
                    "lowestSaleListingPrice": 660000,
                    "auctionNumberAuctioned": 3,
                    "auctionNumberSold": 1,
                    "auctionNumberWithdrawn": null,
                    "daysOnMarket": null,
                    "discountPercentage": null,
                    "medianRentListingPrice": 860,
                    "numberRentListing": 40,
                    "highestRentListingPrice": 2500,
                    "lowestRentListingPrice": 545
                }
            },
            {
                "year": 2012,
                "month": 9,
                "values": {
                    "medianSoldPrice": 1115000,
                    "numberSold": 19,
                    "highestSoldPrice": 5000000,
                    "lowestSoldPrice": 730000,
                    "5thPercentileSoldPrice": 730000,
                    "25thPercentileSoldPrice": 865000,
                    "75thPercentileSoldPrice": 1900000,
                    "95thPercentileSoldPrice": 5000000,
                    "medianSaleListingPrice": 1325000,
                    "numberSaleListing": 26,
                    "highestSaleListingPrice": 5000000,
                    "lowestSaleListingPrice": 815000,
                    "auctionNumberAuctioned": 5,
                    "auctionNumberSold": 2,
                    "auctionNumberWithdrawn": null,
                    "daysOnMarket": 95,
                    "discountPercentage": null,
                    "medianRentListingPrice": 800,
                    "numberRentListing": 36,
                    "highestRentListingPrice": 2600,
                    "lowestRentListingPrice": 420
                }
            },
            {
                "year": 2012,
                "month": 12,
                "values": {
                    "medianSoldPrice": 1270000,
                    "numberSold": 17,
                    "highestSoldPrice": 5550000,
                    "lowestSoldPrice": 790000,
                    "5thPercentileSoldPrice": 790000,
                    "25thPercentileSoldPrice": 980000,
                    "75thPercentileSoldPrice": 2275000,
                    "95thPercentileSoldPrice": 5550000,
                    "medianSaleListingPrice": 1250000,
                    "numberSaleListing": 27,
                    "highestSaleListingPrice": 5250000,
                    "lowestSaleListingPrice": 750000,
                    "auctionNumberAuctioned": 8,
                    "auctionNumberSold": 8,
                    "auctionNumberWithdrawn": null,
                    "daysOnMarket": 65,
                    "discountPercentage": null,
                    "medianRentListingPrice": 798,
                    "numberRentListing": 36,
                    "highestRentListingPrice": 2000,
                    "lowestRentListingPrice": 605
                }
            },
            {
                "year": 2013,
                "month": 3,
                "values": {
                    "medianSoldPrice": 1705000,
                    "numberSold": 12,
                    "highestSoldPrice": 3350000,
                    "lowestSoldPrice": 739000,
                    "5thPercentileSoldPrice": 739000,
                    "25thPercentileSoldPrice": 860000,
                    "75thPercentileSoldPrice": 2100000,
                    "95thPercentileSoldPrice": 3350000,
                    "medianSaleListingPrice": 1093000,
                    "numberSaleListing": 20,
                    "highestSaleListingPrice": 5250000,
                    "lowestSaleListingPrice": 619000,
                    "auctionNumberAuctioned": 8,
                    "auctionNumberSold": 6,
                    "auctionNumberWithdrawn": null,
                    "daysOnMarket": null,
                    "discountPercentage": null,
                    "medianRentListingPrice": 845,
                    "numberRentListing": 36,
                    "highestRentListingPrice": 1850,
                    "lowestRentListingPrice": 625
                }
            },
            {
                "year": 2013,
                "month": 6,
                "values": {
                    "medianSoldPrice": 1400000,
                    "numberSold": 21,
                    "highestSoldPrice": 4375000,
                    "lowestSoldPrice": 860000,
                    "5thPercentileSoldPrice": 875000,
                    "25thPercentileSoldPrice": 1010000,
                    "75thPercentileSoldPrice": 1970000,
                    "95thPercentileSoldPrice": 4265000,
                    "medianSaleListingPrice": 1600000,
                    "numberSaleListing": 29,
                    "highestSaleListingPrice": 5250000,
                    "lowestSaleListingPrice": 899000,
                    "auctionNumberAuctioned": 17,
                    "auctionNumberSold": 10,
                    "auctionNumberWithdrawn": null,
                    "daysOnMarket": 53,
                    "discountPercentage": null,
                    "medianRentListingPrice": 860,
                    "numberRentListing": 40,
                    "highestRentListingPrice": 2200,
                    "lowestRentListingPrice": 550
                }
            },
            {
                "year": 2013,
                "month": 9,
                "values": {
                    "medianSoldPrice": 1370000,
                    "numberSold": 12,
                    "highestSoldPrice": 2400000,
                    "lowestSoldPrice": 875000,
                    "5thPercentileSoldPrice": 875000,
                    "25thPercentileSoldPrice": 1015000,
                    "75thPercentileSoldPrice": 1780000,
                    "95thPercentileSoldPrice": 2400000,
                    "medianSaleListingPrice": 1400000,
                    "numberSaleListing": 24,
                    "highestSaleListingPrice": 5500000,
                    "lowestSaleListingPrice": 750000,
                    "auctionNumberAuctioned": 8,
                    "auctionNumberSold": 4,
                    "auctionNumberWithdrawn": null,
                    "daysOnMarket": null,
                    "discountPercentage": null,
                    "medianRentListingPrice": 900,
                    "numberRentListing": 30,
                    "highestRentListingPrice": 2000,
                    "lowestRentListingPrice": 525
                }
            },
            {
                "year": 2013,
                "month": 12,
                "values": {
                    "medianSoldPrice": 1758000,
                    "numberSold": 28,
                    "highestSoldPrice": 5900000,
                    "lowestSoldPrice": 900000,
                    "5thPercentileSoldPrice": 950000,
                    "25thPercentileSoldPrice": 1226000,
                    "75thPercentileSoldPrice": 2400000,
                    "95thPercentileSoldPrice": 5850000,
                    "medianSaleListingPrice": 1700000,
                    "numberSaleListing": 29,
                    "highestSaleListingPrice": 5985000,
                    "lowestSaleListingPrice": 900000,
                    "auctionNumberAuctioned": 21,
                    "auctionNumberSold": 15,
                    "auctionNumberWithdrawn": null,
                    "daysOnMarket": 69,
                    "discountPercentage": null,
                    "medianRentListingPrice": 850,
                    "numberRentListing": 35,
                    "highestRentListingPrice": 2000,
                    "lowestRentListingPrice": 560
                }
            },
            {
                "year": 2014,
                "month": 3,
                "values": {
                    "medianSoldPrice": 1495000,
                    "numberSold": 14,
                    "highestSoldPrice": 4050000,
                    "lowestSoldPrice": 900000,
                    "5thPercentileSoldPrice": 900000,
                    "25thPercentileSoldPrice": 1276000,
                    "75thPercentileSoldPrice": 1825000,
                    "95thPercentileSoldPrice": 4050000,
                    "medianSaleListingPrice": 1650000,
                    "numberSaleListing": 25,
                    "highestSaleListingPrice": 4400000,
                    "lowestSaleListingPrice": 848000,
                    "auctionNumberAuctioned": 11,
                    "auctionNumberSold": 8,
                    "auctionNumberWithdrawn": null,
                    "daysOnMarket": null,
                    "discountPercentage": null,
                    "medianRentListingPrice": 933,
                    "numberRentListing": 32,
                    "highestRentListingPrice": 3492,
                    "lowestRentListingPrice": 490
                }
            },
            {
                "year": 2014,
                "month": 6,
                "values": {
                    "medianSoldPrice": 2085000,
                    "numberSold": 20,
                    "highestSoldPrice": 3825000,
                    "lowestSoldPrice": 1006000,
                    "5thPercentileSoldPrice": 1006000,
                    "25thPercentileSoldPrice": 1440000,
                    "75thPercentileSoldPrice": 2515000,
                    "95thPercentileSoldPrice": 3825000,
                    "medianSaleListingPrice": 2050000,
                    "numberSaleListing": 23,
                    "highestSaleListingPrice": 6000000,
                    "lowestSaleListingPrice": 950000,
                    "auctionNumberAuctioned": 14,
                    "auctionNumberSold": 13,
                    "auctionNumberWithdrawn": null,
                    "daysOnMarket": 57,
                    "discountPercentage": null,
                    "medianRentListingPrice": 895,
                    "numberRentListing": 25,
                    "highestRentListingPrice": 3100,
                    "lowestRentListingPrice": 580
                }
            },
            {
                "year": 2014,
                "month": 9,
                "values": {
                    "medianSoldPrice": 1969000,
                    "numberSold": 10,
                    "highestSoldPrice": 5600000,
                    "lowestSoldPrice": 1227000,
                    "5thPercentileSoldPrice": 1227000,
                    "25thPercentileSoldPrice": 1372000,
                    "75thPercentileSoldPrice": 2550000,
                    "95thPercentileSoldPrice": 5600000,
                    "medianSaleListingPrice": 2050000,
                    "numberSaleListing": 19,
                    "highestSaleListingPrice": 10000000,
                    "lowestSaleListingPrice": 1050000,
                    "auctionNumberAuctioned": 9,
                    "auctionNumberSold": 7,
                    "auctionNumberWithdrawn": null,
                    "daysOnMarket": null,
                    "discountPercentage": null,
                    "medianRentListingPrice": 795,
                    "numberRentListing": 29,
                    "highestRentListingPrice": 1900,
                    "lowestRentListingPrice": 550
                }
            },
            {
                "year": 2014,
                "month": 12,
                "values": {
                    "medianSoldPrice": 1660000,
                    "numberSold": 20,
                    "highestSoldPrice": 4000000,
                    "lowestSoldPrice": 960000,
                    "5thPercentileSoldPrice": 960000,
                    "25thPercentileSoldPrice": 1210000,
                    "75thPercentileSoldPrice": 2050000,
                    "95thPercentileSoldPrice": 3760000,
                    "medianSaleListingPrice": 1845000,
                    "numberSaleListing": 22,
                    "highestSaleListingPrice": 10000000,
                    "lowestSaleListingPrice": 850000,
                    "auctionNumberAuctioned": 17,
                    "auctionNumberSold": 9,
                    "auctionNumberWithdrawn": null,
                    "daysOnMarket": 36,
                    "discountPercentage": null,
                    "medianRentListingPrice": 900,
                    "numberRentListing": 27,
                    "highestRentListingPrice": 6000,
                    "lowestRentListingPrice": 680
                }
            },
            {
                "year": 2015,
                "month": 3,
                "values": {
                    "medianSoldPrice": 1991000,
                    "numberSold": 16,
                    "highestSoldPrice": 3575000,
                    "lowestSoldPrice": 930000,
                    "5thPercentileSoldPrice": 930000,
                    "25thPercentileSoldPrice": 1185000,
                    "75thPercentileSoldPrice": 2490000,
                    "95thPercentileSoldPrice": 3575000,
                    "medianSaleListingPrice": 1813000,
                    "numberSaleListing": 19,
                    "highestSaleListingPrice": 5000000,
                    "lowestSaleListingPrice": 870000,
                    "auctionNumberAuctioned": 8,
                    "auctionNumberSold": 6,
                    "auctionNumberWithdrawn": null,
                    "daysOnMarket": 43,
                    "discountPercentage": null,
                    "medianRentListingPrice": 1095,
                    "numberRentListing": 39,
                    "highestRentListingPrice": 3200,
                    "lowestRentListingPrice": 550
                }
            },
            {
                "year": 2015,
                "month": 6,
                "values": {
                    "medianSoldPrice": 1550000,
                    "numberSold": 11,
                    "highestSoldPrice": 2650000,
                    "lowestSoldPrice": 1051000,
                    "5thPercentileSoldPrice": 1051000,
                    "25thPercentileSoldPrice": 1435000,
                    "75thPercentileSoldPrice": 2107000,
                    "95thPercentileSoldPrice": 2650000,
                    "medianSaleListingPrice": 2250000,
                    "numberSaleListing": 18,
                    "highestSaleListingPrice": 5985000,
                    "lowestSaleListingPrice": 1000000,
                    "auctionNumberAuctioned": 7,
                    "auctionNumberSold": 5,
                    "auctionNumberWithdrawn": null,
                    "daysOnMarket": null,
                    "discountPercentage": null,
                    "medianRentListingPrice": 1150,
                    "numberRentListing": 33,
                    "highestRentListingPrice": 3200,
                    "lowestRentListingPrice": 520
                }
            },
            {
                "year": 2015,
                "month": 9,
                "values": {
                    "medianSoldPrice": 2250000,
                    "numberSold": 23,
                    "highestSoldPrice": 6500000,
                    "lowestSoldPrice": 1078000,
                    "5thPercentileSoldPrice": 1200000,
                    "25thPercentileSoldPrice": 1450000,
                    "75thPercentileSoldPrice": 3075000,
                    "95thPercentileSoldPrice": 4550000,
                    "medianSaleListingPrice": 1800000,
                    "numberSaleListing": 23,
                    "highestSaleListingPrice": 5985000,
                    "lowestSaleListingPrice": 900000,
                    "auctionNumberAuctioned": 14,
                    "auctionNumberSold": 13,
                    "auctionNumberWithdrawn": null,
                    "daysOnMarket": 21,
                    "discountPercentage": null,
                    "medianRentListingPrice": 900,
                    "numberRentListing": 31,
                    "highestRentListingPrice": 3200,
                    "lowestRentListingPrice": 655
                }
            },
            {
                "year": 2015,
                "month": 12,
                "values": {
                    "medianSoldPrice": 1725000,
                    "numberSold": 14,
                    "highestSoldPrice": 6025000,
                    "lowestSoldPrice": 1300000,
                    "5thPercentileSoldPrice": 1300000,
                    "25thPercentileSoldPrice": 1360000,
                    "75thPercentileSoldPrice": 3000000,
                    "95thPercentileSoldPrice": 6025000,
                    "medianSaleListingPrice": 2750000,
                    "numberSaleListing": 15,
                    "highestSaleListingPrice": 8728000,
                    "lowestSaleListingPrice": 1200000,
                    "auctionNumberAuctioned": 10,
                    "auctionNumberSold": 7,
                    "auctionNumberWithdrawn": null,
                    "daysOnMarket": null,
                    "discountPercentage": null,
                    "medianRentListingPrice": 950,
                    "numberRentListing": 27,
                    "highestRentListingPrice": 2750,
                    "lowestRentListingPrice": 580
                }
            },
            {
                "year": 2016,
                "month": 3,
                "values": {
                    "medianSoldPrice": 1561000,
                    "numberSold": 12,
                    "highestSoldPrice": 8500000,
                    "lowestSoldPrice": 840000,
                    "5thPercentileSoldPrice": 840000,
                    "25thPercentileSoldPrice": 1090000,
                    "75thPercentileSoldPrice": 2180000,
                    "95thPercentileSoldPrice": 8500000,
                    "medianSaleListingPrice": 2180000,
                    "numberSaleListing": 15,
                    "highestSaleListingPrice": 8728000,
                    "lowestSaleListingPrice": 590000,
                    "auctionNumberAuctioned": 10,
                    "auctionNumberSold": 5,
                    "auctionNumberWithdrawn": null,
                    "daysOnMarket": null,
                    "discountPercentage": null,
                    "medianRentListingPrice": 950,
                    "numberRentListing": 27,
                    "highestRentListingPrice": 2000,
                    "lowestRentListingPrice": 590
                }
            },
            {
                "year": 2016,
                "month": 6,
                "values": {
                    "medianSoldPrice": 1750000,
                    "numberSold": 14,
                    "highestSoldPrice": 7500000,
                    "lowestSoldPrice": 1030000,
                    "5thPercentileSoldPrice": 1030000,
                    "25thPercentileSoldPrice": 1450000,
                    "75thPercentileSoldPrice": 4350000,
                    "95thPercentileSoldPrice": 7500000,
                    "medianSaleListingPrice": 1746000,
                    "numberSaleListing": 16,
                    "highestSaleListingPrice": 5500000,
                    "lowestSaleListingPrice": 1150000,
                    "auctionNumberAuctioned": 10,
                    "auctionNumberSold": 8,
                    "auctionNumberWithdrawn": null,
                    "daysOnMarket": null,
                    "discountPercentage": null,
                    "medianRentListingPrice": 970,
                    "numberRentListing": 25,
                    "highestRentListingPrice": 2400,
                    "lowestRentListingPrice": 595
                }
            },
            {
                "year": 2016,
                "month": 9,
                "values": {
                    "medianSoldPrice": 1505000,
                    "numberSold": 20,
                    "highestSoldPrice": 6750000,
                    "lowestSoldPrice": 1325000,
                    "5thPercentileSoldPrice": 1325000,
                    "25thPercentileSoldPrice": 1428000,
                    "75thPercentileSoldPrice": 3500000,
                    "95thPercentileSoldPrice": 6750000,
                    "medianSaleListingPrice": 1700000,
                    "numberSaleListing": 21,
                    "highestSaleListingPrice": 5500000,
                    "lowestSaleListingPrice": 900000,
                    "auctionNumberAuctioned": 15,
                    "auctionNumberSold": 13,
                    "auctionNumberWithdrawn": null,
                    "daysOnMarket": 31,
                    "discountPercentage": null,
                    "medianRentListingPrice": 950,
                    "numberRentListing": 18,
                    "highestRentListingPrice": 2400,
                    "lowestRentListingPrice": 540
                }
            },
            {
                "year": 2016,
                "month": 12,
                "values": {
                    "medianSoldPrice": 2190000,
                    "numberSold": 19,
                    "highestSoldPrice": 6500000,
                    "lowestSoldPrice": 1550000,
                    "5thPercentileSoldPrice": 1550000,
                    "25thPercentileSoldPrice": 1870000,
                    "75thPercentileSoldPrice": 3750000,
                    "95thPercentileSoldPrice": 6500000,
                    "medianSaleListingPrice": null,
                    "numberSaleListing": 14,
                    "highestSaleListingPrice": 3600000,
                    "lowestSaleListingPrice": 900000,
                    "auctionNumberAuctioned": 11,
                    "auctionNumberSold": 10,
                    "auctionNumberWithdrawn": null,
                    "daysOnMarket": 29,
                    "discountPercentage": null,
                    "medianRentListingPrice": 900,
                    "numberRentListing": 33,
                    "highestRentListingPrice": 1800,
                    "lowestRentListingPrice": 450
                }
            },
            {
                "year": 2017,
                "month": 3,
                "values": {
                    "medianSoldPrice": null,
                    "numberSold": 7,
                    "highestSoldPrice": 3800000,
                    "lowestSoldPrice": 1425000,
                    "5thPercentileSoldPrice": null,
                    "25thPercentileSoldPrice": null,
                    "75thPercentileSoldPrice": null,
                    "95thPercentileSoldPrice": null,
                    "medianSaleListingPrice": null,
                    "numberSaleListing": 10,
                    "highestSaleListingPrice": 7500000,
                    "lowestSaleListingPrice": 1350000,
                    "auctionNumberAuctioned": 3,
                    "auctionNumberSold": 3,
                    "auctionNumberWithdrawn": null,
                    "daysOnMarket": null,
                    "discountPercentage": null,
                    "medianRentListingPrice": 1000,
                    "numberRentListing": 32,
                    "highestRentListingPrice": 2500,
                    "lowestRentListingPrice": 625
                }
            },
            {
                "year": 2017,
                "month": 6,
                "values": {
                    "medianSoldPrice": 2450000,
                    "numberSold": 14,
                    "highestSoldPrice": 11750000,
                    "lowestSoldPrice": 1275000,
                    "5thPercentileSoldPrice": 1275000,
                    "25thPercentileSoldPrice": 1968000,
                    "75thPercentileSoldPrice": 3700000,
                    "95thPercentileSoldPrice": 11750000,
                    "medianSaleListingPrice": 2350000,
                    "numberSaleListing": 17,
                    "highestSaleListingPrice": 7500000,
                    "lowestSaleListingPrice": 1200000,
                    "auctionNumberAuctioned": 10,
                    "auctionNumberSold": 8,
                    "auctionNumberWithdrawn": null,
                    "daysOnMarket": null,
                    "discountPercentage": null,
                    "medianRentListingPrice": 950,
                    "numberRentListing": 31,
                    "highestRentListingPrice": 5000,
                    "lowestRentListingPrice": 550
                }
            },
            {
                "year": 2017,
                "month": 9,
                "values": {
                    "medianSoldPrice": 1827000,
                    "numberSold": 17,
                    "highestSoldPrice": 8300000,
                    "lowestSoldPrice": 1275000,
                    "5thPercentileSoldPrice": 1275000,
                    "25thPercentileSoldPrice": 1656000,
                    "75thPercentileSoldPrice": 2850000,
                    "95thPercentileSoldPrice": 8300000,
                    "medianSaleListingPrice": 1850000,
                    "numberSaleListing": 16,
                    "highestSaleListingPrice": 6500000,
                    "lowestSaleListingPrice": 1275000,
                    "auctionNumberAuctioned": 9,
                    "auctionNumberSold": 6,
                    "auctionNumberWithdrawn": null,
                    "daysOnMarket": 37,
                    "discountPercentage": null,
                    "medianRentListingPrice": 1000,
                    "numberRentListing": 21,
                    "highestRentListingPrice": 5500,
                    "lowestRentListingPrice": 660
                }
            },
            {
                "year": 2017,
                "month": 12,
                "values": {
                    "medianSoldPrice": 1725000,
                    "numberSold": 15,
                    "highestSoldPrice": 7225000,
                    "lowestSoldPrice": 1260000,
                    "5thPercentileSoldPrice": 1260000,
                    "25thPercentileSoldPrice": 1414000,
                    "75thPercentileSoldPrice": 3385000,
                    "95thPercentileSoldPrice": 7225000,
                    "medianSaleListingPrice": 2033000,
                    "numberSaleListing": 22,
                    "highestSaleListingPrice": 11750000,
                    "lowestSaleListingPrice": 1290000,
                    "auctionNumberAuctioned": 11,
                    "auctionNumberSold": 7,
                    "auctionNumberWithdrawn": null,
                    "daysOnMarket": null,
                    "discountPercentage": null,
                    "medianRentListingPrice": 1050,
                    "numberRentListing": 26,
                    "highestRentListingPrice": 5500,
                    "lowestRentListingPrice": 580
                }
            },
            {
                "year": 2018,
                "month": 3,
                "values": {
                    "medianSoldPrice": null,
                    "numberSold": 7,
                    "highestSoldPrice": 5311000,
                    "lowestSoldPrice": 1040000,
                    "5thPercentileSoldPrice": null,
                    "25thPercentileSoldPrice": null,
                    "75thPercentileSoldPrice": null,
                    "95thPercentileSoldPrice": null,
                    "medianSaleListingPrice": null,
                    "numberSaleListing": 9,
                    "highestSaleListingPrice": 5311000,
                    "lowestSaleListingPrice": 1450000,
                    "auctionNumberAuctioned": 4,
                    "auctionNumberSold": 3,
                    "auctionNumberWithdrawn": null,
                    "daysOnMarket": null,
                    "discountPercentage": null,
                    "medianRentListingPrice": 848,
                    "numberRentListing": 36,
                    "highestRentListingPrice": 2000,
                    "lowestRentListingPrice": 575
                }
            },
            {
                "year": 2018,
                "month": 6,
                "values": {
                    "medianSoldPrice": null,
                    "numberSold": 10,
                    "highestSoldPrice": 2200000,
                    "lowestSoldPrice": 1380000,
                    "5thPercentileSoldPrice": null,
                    "25thPercentileSoldPrice": null,
                    "75thPercentileSoldPrice": null,
                    "95thPercentileSoldPrice": null,
                    "medianSaleListingPrice": 1950000,
                    "numberSaleListing": 13,
                    "highestSaleListingPrice": 6000000,
                    "lowestSaleListingPrice": 1380000,
                    "auctionNumberAuctioned": 7,
                    "auctionNumberSold": 4,
                    "auctionNumberWithdrawn": null,
                    "daysOnMarket": null,
                    "discountPercentage": null,
                    "medianRentListingPrice": 940,
                    "numberRentListing": 30,
                    "highestRentListingPrice": 2000,
                    "lowestRentListingPrice": 575
                }
            },
            {
                "year": 2018,
                "month": 9,
                "values": {
                    "medianSoldPrice": 2189000,
                    "numberSold": 12,
                    "highestSoldPrice": 6300000,
                    "lowestSoldPrice": 1180000,
                    "5thPercentileSoldPrice": 1180000,
                    "25thPercentileSoldPrice": 1400000,
                    "75thPercentileSoldPrice": 2425000,
                    "95thPercentileSoldPrice": 6300000,
                    "medianSaleListingPrice": 2200000,
                    "numberSaleListing": 17,
                    "highestSaleListingPrice": 9250000,
                    "lowestSaleListingPrice": 1035000,
                    "auctionNumberAuctioned": 10,
                    "auctionNumberSold": 6,
                    "auctionNumberWithdrawn": null,
                    "daysOnMarket": null,
                    "discountPercentage": null,
                    "medianRentListingPrice": 965,
                    "numberRentListing": 31,
                    "highestRentListingPrice": 2000,
                    "lowestRentListingPrice": 545
                }
            },
            {
                "year": 2018,
                "month": 12,
                "values": {
                    "medianSoldPrice": 1933000,
                    "numberSold": 10,
                    "highestSoldPrice": 6100000,
                    "lowestSoldPrice": 1370000,
                    "5thPercentileSoldPrice": 1370000,
                    "25thPercentileSoldPrice": 1615000,
                    "75thPercentileSoldPrice": 4750000,
                    "95thPercentileSoldPrice": 6100000,
                    "medianSaleListingPrice": 2085000,
                    "numberSaleListing": 18,
                    "highestSaleListingPrice": 9250000,
                    "lowestSaleListingPrice": 1035000,
                    "auctionNumberAuctioned": 8,
                    "auctionNumberSold": 2,
                    "auctionNumberWithdrawn": null,
                    "daysOnMarket": null,
                    "discountPercentage": null,
                    "medianRentListingPrice": 930,
                    "numberRentListing": 35,
                    "highestRentListingPrice": 5000,
                    "lowestRentListingPrice": 550
                }
            },
            {
                "year": 2019,
                "month": 3,
                "values": {
                    "medianSoldPrice": 1550000,
                    "numberSold": 13,
                    "highestSoldPrice": 14250000,
                    "lowestSoldPrice": 965000,
                    "5thPercentileSoldPrice": 965000,
                    "25thPercentileSoldPrice": 1260000,
                    "75thPercentileSoldPrice": 1670000,
                    "95thPercentileSoldPrice": 14250000,
                    "medianSaleListingPrice": 1550000,
                    "numberSaleListing": 18,
                    "highestSaleListingPrice": 8750000,
                    "lowestSaleListingPrice": 950000,
                    "auctionNumberAuctioned": 4,
                    "auctionNumberSold": 3,
                    "auctionNumberWithdrawn": null,
                    "daysOnMarket": null,
                    "discountPercentage": null,
                    "medianRentListingPrice": 998,
                    "numberRentListing": 42,
                    "highestRentListingPrice": 4500,
                    "lowestRentListingPrice": 590
                }
            },
            {
                "year": 2019,
                "month": 6,
                "values": {
                    "medianSoldPrice": 2875000,
                    "numberSold": 13,
                    "highestSoldPrice": 7660000,
                    "lowestSoldPrice": 978000,
                    "5thPercentileSoldPrice": 978000,
                    "25thPercentileSoldPrice": 1525000,
                    "75thPercentileSoldPrice": 3200000,
                    "95thPercentileSoldPrice": 7660000,
                    "medianSaleListingPrice": 2250000,
                    "numberSaleListing": 12,
                    "highestSaleListingPrice": 7350000,
                    "lowestSaleListingPrice": 950000,
                    "auctionNumberAuctioned": 7,
                    "auctionNumberSold": 5,
                    "auctionNumberWithdrawn": null,
                    "daysOnMarket": null,
                    "discountPercentage": null,
                    "medianRentListingPrice": 915,
                    "numberRentListing": 22,
                    "highestRentListingPrice": 2600,
                    "lowestRentListingPrice": 605
                }
            },
            {
                "year": 2019,
                "month": 9,
                "values": {
                    "medianSoldPrice": null,
                    "numberSold": 9,
                    "highestSoldPrice": 5500000,
                    "lowestSoldPrice": 1050000,
                    "5thPercentileSoldPrice": null,
                    "25thPercentileSoldPrice": null,
                    "75thPercentileSoldPrice": null,
                    "95thPercentileSoldPrice": null,
                    "medianSaleListingPrice": null,
                    "numberSaleListing": 11,
                    "highestSaleListingPrice": 7350000,
                    "lowestSaleListingPrice": 950000,
                    "auctionNumberAuctioned": 6,
                    "auctionNumberSold": 6,
                    "auctionNumberWithdrawn": null,
                    "daysOnMarket": null,
                    "discountPercentage": null,
                    "medianRentListingPrice": 950,
                    "numberRentListing": 30,
                    "highestRentListingPrice": 2600,
                    "lowestRentListingPrice": 595
                }
            },
            {
                "year": 2019,
                "month": 12,
                "values": {
                    "medianSoldPrice": 2015000,
                    "numberSold": 14,
                    "highestSoldPrice": 7000000,
                    "lowestSoldPrice": 1360000,
                    "5thPercentileSoldPrice": 1360000,
                    "25thPercentileSoldPrice": 1800000,
                    "75thPercentileSoldPrice": 2413000,
                    "95thPercentileSoldPrice": 7000000,
                    "medianSaleListingPrice": null,
                    "numberSaleListing": 12,
                    "highestSaleListingPrice": 7350000,
                    "lowestSaleListingPrice": 1100000,
                    "auctionNumberAuctioned": 9,
                    "auctionNumberSold": 8,
                    "auctionNumberWithdrawn": null,
                    "daysOnMarket": null,
                    "discountPercentage": null,
                    "medianRentListingPrice": 950,
                    "numberRentListing": 33,
                    "highestRentListingPrice": 2950,
                    "lowestRentListingPrice": 640
                }
            },
            {
                "year": 2020,
                "month": 3,
                "values": {
                    "medianSoldPrice": 2105000,
                    "numberSold": 10,
                    "highestSoldPrice": 3400000,
                    "lowestSoldPrice": 1150000,
                    "5thPercentileSoldPrice": 1150000,
                    "25thPercentileSoldPrice": 1888000,
                    "75thPercentileSoldPrice": 2360000,
                    "95thPercentileSoldPrice": 3400000,
                    "medianSaleListingPrice": null,
                    "numberSaleListing": 16,
                    "highestSaleListingPrice": 7350000,
                    "lowestSaleListingPrice": 1100000,
                    "auctionNumberAuctioned": 11,
                    "auctionNumberSold": 7,
                    "auctionNumberWithdrawn": null,
                    "daysOnMarket": null,
                    "discountPercentage": null,
                    "medianRentListingPrice": 1000,
                    "numberRentListing": 39,
                    "highestRentListingPrice": 3500,
                    "lowestRentListingPrice": 600
                }
            },
            {
                "year": 2020,
                "month": 6,
                "values": {
                    "medianSoldPrice": 2200000,
                    "numberSold": 17,
                    "highestSoldPrice": 5600000,
                    "lowestSoldPrice": 1000000,
                    "5thPercentileSoldPrice": 1000000,
                    "25thPercentileSoldPrice": 1850000,
                    "75thPercentileSoldPrice": 3000000,
                    "95thPercentileSoldPrice": 5600000,
                    "medianSaleListingPrice": 2000000,
                    "numberSaleListing": 28,
                    "highestSaleListingPrice": 7350000,
                    "lowestSaleListingPrice": 1100000,
                    "auctionNumberAuctioned": 8,
                    "auctionNumberSold": 6,
                    "auctionNumberWithdrawn": null,
                    "daysOnMarket": null,
                    "discountPercentage": null,
                    "medianRentListingPrice": 900,
                    "numberRentListing": 41,
                    "highestRentListingPrice": 4390,
                    "lowestRentListingPrice": 500
                }
            },
            {
                "year": 2020,
                "month": 9,
                "values": {
                    "medianSoldPrice": 2168000,
                    "numberSold": 20,
                    "highestSoldPrice": 4650000,
                    "lowestSoldPrice": 1500000,
                    "5thPercentileSoldPrice": 1500000,
                    "25thPercentileSoldPrice": 1800000,
                    "75thPercentileSoldPrice": 2725000,
                    "95thPercentileSoldPrice": 3300000,
                    "medianSaleListingPrice": 2000000,
                    "numberSaleListing": 23,
                    "highestSaleListingPrice": 5500000,
                    "lowestSaleListingPrice": 1500000,
                    "auctionNumberAuctioned": 7,
                    "auctionNumberSold": 6,
                    "auctionNumberWithdrawn": null,
                    "daysOnMarket": 24,
                    "discountPercentage": null,
                    "medianRentListingPrice": 948,
                    "numberRentListing": 34,
                    "highestRentListingPrice": 3200,
                    "lowestRentListingPrice": 540
                }
            },
            {
                "year": 2020,
                "month": 12,
                "values": {
                    "medianSoldPrice": 2305000,
                    "numberSold": 13,
                    "highestSoldPrice": 5600000,
                    "lowestSoldPrice": 1550000,
                    "5thPercentileSoldPrice": 1550000,
                    "25thPercentileSoldPrice": 1680000,
                    "75thPercentileSoldPrice": 2700000,
                    "95thPercentileSoldPrice": 5600000,
                    "medianSaleListingPrice": null,
                    "numberSaleListing": 11,
                    "highestSaleListingPrice": 3600000,
                    "lowestSaleListingPrice": 1400000,
                    "auctionNumberAuctioned": 8,
                    "auctionNumberSold": 7,
                    "auctionNumberWithdrawn": null,
                    "daysOnMarket": null,
                    "discountPercentage": null,
                    "medianRentListingPrice": 900,
                    "numberRentListing": 25,
                    "highestRentListingPrice": 1800,
                    "lowestRentListingPrice": 580
                }
            },
            {
                "year": 2021,
                "month": 3,
                "values": {
                    "medianSoldPrice": 3365000,
                    "numberSold": 12,
                    "highestSoldPrice": 8170000,
                    "lowestSoldPrice": 2100000,
                    "5thPercentileSoldPrice": 2100000,
                    "25thPercentileSoldPrice": 2700000,
                    "75thPercentileSoldPrice": 4450000,
                    "95thPercentileSoldPrice": 8170000,
                    "medianSaleListingPrice": 2700000,
                    "numberSaleListing": 13,
                    "highestSaleListingPrice": 4300000,
                    "lowestSaleListingPrice": 2000000,
                    "auctionNumberAuctioned": 7,
                    "auctionNumberSold": 6,
                    "auctionNumberWithdrawn": null,
                    "daysOnMarket": null,
                    "discountPercentage": null,
                    "medianRentListingPrice": 1000,
                    "numberRentListing": 26,
                    "highestRentListingPrice": 3000,
                    "lowestRentListingPrice": 500
                }
            },
            {
                "year": 2021,
                "month": 6,
                "values": {
                    "medianSoldPrice": 2850000,
                    "numberSold": 20,
                    "highestSoldPrice": 5400000,
                    "lowestSoldPrice": 1250000,
                    "5thPercentileSoldPrice": 1250000,
                    "25thPercentileSoldPrice": 2350000,
                    "75thPercentileSoldPrice": 3448000,
                    "95thPercentileSoldPrice": 5400000,
                    "medianSaleListingPrice": 2425000,
                    "numberSaleListing": 24,
                    "highestSaleListingPrice": 4250000,
                    "lowestSaleListingPrice": 1050000,
                    "auctionNumberAuctioned": 18,
                    "auctionNumberSold": 17,
                    "auctionNumberWithdrawn": null,
                    "daysOnMarket": 17,
                    "discountPercentage": null,
                    "medianRentListingPrice": 1025,
                    "numberRentListing": 24,
                    "highestRentListingPrice": 3500,
                    "lowestRentListingPrice": 400
                }
            }
        ]
    }
}