{
    "header": {
        "suburb": "Middle Dural",
        "state": "NSW",
        "propertyCategory": "House"
    },
    "series": {
        "seriesInfo": [
            {
                "year": 2011,
                "month": 9,
                "values": {
                    "medianSoldPrice": null,
                    "numberSold": null,
                    "highestSoldPrice": null,
                    "lowestSoldPrice": null,
                    "5thPercentileSoldPrice": null,
                    "25thPercentileSoldPrice": null,
                    "75thPercentileSoldPrice": null,
                    "95thPercentileSoldPrice": null,
                    "medianSaleListingPrice": null,
                    "numberSaleListing": 6,
                    "highestSaleListingPrice": 2800000,
                    "lowestSaleListingPrice": 1750000,
                    "auctionNumberAuctioned": null,
                    "auctionNumberSold": null,
                    "auctionNumberWithdrawn": null,
                    "daysOnMarket": null,
                    "discountPercentage": null,
                    "medianRentListingPrice": null,
                    "numberRentListing": 5,
                    "highestRentListingPrice": 1600,
                    "lowestRentListingPrice": 450
                }
            },
            {
                "year": 2011,
                "month": 12,
                "values": {
                    "medianSoldPrice": null,
                    "numberSold": 1,
                    "highestSoldPrice": 1785000,
                    "lowestSoldPrice": 1785000,
                    "5thPercentileSoldPrice": null,
                    "25thPercentileSoldPrice": null,
                    "75thPercentileSoldPrice": null,
                    "95thPercentileSoldPrice": null,
                    "medianSaleListingPrice": null,
                    "numberSaleListing": 7,
                    "highestSaleListingPrice": 2800000,
                    "lowestSaleListingPrice": 1500000,
                    "auctionNumberAuctioned": null,
                    "auctionNumberSold": null,
                    "auctionNumberWithdrawn": null,
                    "daysOnMarket": null,
                    "discountPercentage": null,
                    "medianRentListingPrice": null,
                    "numberRentListing": 3,
                    "highestRentListingPrice": 1300,
                    "lowestRentListingPrice": 820
                }
            },
            {
                "year": 2012,
                "month": 3,
                "values": {
                    "medianSoldPrice": null,
                    "numberSold": null,
                    "highestSoldPrice": null,
                    "lowestSoldPrice": null,
                    "5thPercentileSoldPrice": null,
                    "25thPercentileSoldPrice": null,
                    "75thPercentileSoldPrice": null,
                    "95thPercentileSoldPrice": null,
                    "medianSaleListingPrice": null,
                    "numberSaleListing": 7,
                    "highestSaleListingPrice": 2800000,
                    "lowestSaleListingPrice": 795000,
                    "auctionNumberAuctioned": null,
                    "auctionNumberSold": null,
                    "auctionNumberWithdrawn": null,
                    "daysOnMarket": null,
                    "discountPercentage": null,
                    "medianRentListingPrice": null,
                    "numberRentListing": 7,
                    "highestRentListingPrice": 1100,
                    "lowestRentListingPrice": 300
                }
            },
            {
                "year": 2012,
                "month": 6,
                "values": {
                    "medianSoldPrice": null,
                    "numberSold": null,
                    "highestSoldPrice": null,
                    "lowestSoldPrice": null,
                    "5thPercentileSoldPrice": null,
                    "25thPercentileSoldPrice": null,
                    "75thPercentileSoldPrice": null,
                    "95thPercentileSoldPrice": null,
                    "medianSaleListingPrice": null,
                    "numberSaleListing": 3,
                    "highestSaleListingPrice": 2800000,
                    "lowestSaleListingPrice": 700000,
                    "auctionNumberAuctioned": null,
                    "auctionNumberSold": null,
                    "auctionNumberWithdrawn": null,
                    "daysOnMarket": null,
                    "discountPercentage": null,
                    "medianRentListingPrice": null,
                    "numberRentListing": 2,
                    "highestRentListingPrice": 1400,
                    "lowestRentListingPrice": 800
                }
            },
            {
                "year": 2012,
                "month": 9,
                "values": {
                    "medianSoldPrice": null,
                    "numberSold": null,
                    "highestSoldPrice": null,
                    "lowestSoldPrice": null,
                    "5thPercentileSoldPrice": null,
                    "25thPercentileSoldPrice": null,
                    "75thPercentileSoldPrice": null,
                    "95thPercentileSoldPrice": null,
                    "medianSaleListingPrice": null,
                    "numberSaleListing": 5,
                    "highestSaleListingPrice": 3980000,
                    "lowestSaleListingPrice": 700000,
                    "auctionNumberAuctioned": null,
                    "auctionNumberSold": null,
                    "auctionNumberWithdrawn": null,
                    "daysOnMarket": null,
                    "discountPercentage": null,
                    "medianRentListingPrice": null,
                    "numberRentListing": 2,
                    "highestRentListingPrice": 770,
                    "lowestRentListingPrice": 415
                }
            },
            {
                "year": 2012,
                "month": 12,
                "values": {
                    "medianSoldPrice": null,
                    "numberSold": null,
                    "highestSoldPrice": null,
                    "lowestSoldPrice": null,
                    "5thPercentileSoldPrice": null,
                    "25thPercentileSoldPrice": null,
                    "75thPercentileSoldPrice": null,
                    "95thPercentileSoldPrice": null,
                    "medianSaleListingPrice": null,
                    "numberSaleListing": 2,
                    "highestSaleListingPrice": 1700000,
                    "lowestSaleListingPrice": 759000,
                    "auctionNumberAuctioned": null,
                    "auctionNumberSold": null,
                    "auctionNumberWithdrawn": null,
                    "daysOnMarket": null,
                    "discountPercentage": null,
                    "medianRentListingPrice": null,
                    "numberRentListing": 5,
                    "highestRentListingPrice": 750,
                    "lowestRentListingPrice": 365
                }
            },
            {
                "year": 2013,
                "month": 3,
                "values": {
                    "medianSoldPrice": null,
                    "numberSold": null,
                    "highestSoldPrice": null,
                    "lowestSoldPrice": null,
                    "5thPercentileSoldPrice": null,
                    "25thPercentileSoldPrice": null,
                    "75thPercentileSoldPrice": null,
                    "95thPercentileSoldPrice": null,
                    "medianSaleListingPrice": null,
                    "numberSaleListing": 5,
                    "highestSaleListingPrice": 4750000,
                    "lowestSaleListingPrice": 409000,
                    "auctionNumberAuctioned": null,
                    "auctionNumberSold": null,
                    "auctionNumberWithdrawn": null,
                    "daysOnMarket": null,
                    "discountPercentage": null,
                    "medianRentListingPrice": null,
                    "numberRentListing": 2,
                    "highestRentListingPrice": 1300,
                    "lowestRentListingPrice": 390
                }
            },
            {
                "year": 2013,
                "month": 6,
                "values": {
                    "medianSoldPrice": null,
                    "numberSold": null,
                    "highestSoldPrice": null,
                    "lowestSoldPrice": null,
                    "5thPercentileSoldPrice": null,
                    "25thPercentileSoldPrice": null,
                    "75thPercentileSoldPrice": null,
                    "95thPercentileSoldPrice": null,
                    "medianSaleListingPrice": null,
                    "numberSaleListing": 5,
                    "highestSaleListingPrice": 4750000,
                    "lowestSaleListingPrice": 725000,
                    "auctionNumberAuctioned": null,
                    "auctionNumberSold": null,
                    "auctionNumberWithdrawn": null,
                    "daysOnMarket": null,
                    "discountPercentage": null,
                    "medianRentListingPrice": null,
                    "numberRentListing": 3,
                    "highestRentListingPrice": 715,
                    "lowestRentListingPrice": 390
                }
            },
            {
                "year": 2013,
                "month": 9,
                "values": {
                    "medianSoldPrice": null,
                    "numberSold": 1,
                    "highestSoldPrice": 1255000,
                    "lowestSoldPrice": 1255000,
                    "5thPercentileSoldPrice": null,
                    "25thPercentileSoldPrice": null,
                    "75thPercentileSoldPrice": null,
                    "95thPercentileSoldPrice": null,
                    "medianSaleListingPrice": null,
                    "numberSaleListing": 2,
                    "highestSaleListingPrice": 1800000,
                    "lowestSaleListingPrice": 1313000,
                    "auctionNumberAuctioned": null,
                    "auctionNumberSold": null,
                    "auctionNumberWithdrawn": null,
                    "daysOnMarket": null,
                    "discountPercentage": null,
                    "medianRentListingPrice": null,
                    "numberRentListing": 4,
                    "highestRentListingPrice": 1500,
                    "lowestRentListingPrice": 450
                }
            },
            {
                "year": 2013,
                "month": 12,
                "values": {
                    "medianSoldPrice": null,
                    "numberSold": null,
                    "highestSoldPrice": null,
                    "lowestSoldPrice": null,
                    "5thPercentileSoldPrice": null,
                    "25thPercentileSoldPrice": null,
                    "75thPercentileSoldPrice": null,
                    "95thPercentileSoldPrice": null,
                    "medianSaleListingPrice": null,
                    "numberSaleListing": 2,
                    "highestSaleListingPrice": 1696000,
                    "lowestSaleListingPrice": 1155000,
                    "auctionNumberAuctioned": null,
                    "auctionNumberSold": null,
                    "auctionNumberWithdrawn": null,
                    "daysOnMarket": null,
                    "discountPercentage": null,
                    "medianRentListingPrice": null,
                    "numberRentListing": 4,
                    "highestRentListingPrice": 1070,
                    "lowestRentListingPrice": 450
                }
            },
            {
                "year": 2014,
                "month": 3,
                "values": {
                    "medianSoldPrice": null,
                    "numberSold": null,
                    "highestSoldPrice": null,
                    "lowestSoldPrice": null,
                    "5thPercentileSoldPrice": null,
                    "25thPercentileSoldPrice": null,
                    "75thPercentileSoldPrice": null,
                    "95thPercentileSoldPrice": null,
                    "medianSaleListingPrice": null,
                    "numberSaleListing": 3,
                    "highestSaleListingPrice": 1696000,
                    "lowestSaleListingPrice": 1150000,
                    "auctionNumberAuctioned": null,
                    "auctionNumberSold": null,
                    "auctionNumberWithdrawn": null,
                    "daysOnMarket": null,
                    "discountPercentage": null,
                    "medianRentListingPrice": null,
                    "numberRentListing": null,
                    "highestRentListingPrice": null,
                    "lowestRentListingPrice": null
                }
            },
            {
                "year": 2014,
                "month": 6,
                "values": {
                    "medianSoldPrice": null,
                    "numberSold": null,
                    "highestSoldPrice": null,
                    "lowestSoldPrice": null,
                    "5thPercentileSoldPrice": null,
                    "25thPercentileSoldPrice": null,
                    "75thPercentileSoldPrice": null,
                    "95thPercentileSoldPrice": null,
                    "medianSaleListingPrice": null,
                    "numberSaleListing": 3,
                    "highestSaleListingPrice": 1400000,
                    "lowestSaleListingPrice": 1103000,
                    "auctionNumberAuctioned": null,
                    "auctionNumberSold": null,
                    "auctionNumberWithdrawn": null,
                    "daysOnMarket": null,
                    "discountPercentage": null,
                    "medianRentListingPrice": null,
                    "numberRentListing": 3,
                    "highestRentListingPrice": 1600,
                    "lowestRentListingPrice": 300
                }
            },
            {
                "year": 2014,
                "month": 9,
                "values": {
                    "medianSoldPrice": null,
                    "numberSold": null,
                    "highestSoldPrice": null,
                    "lowestSoldPrice": null,
                    "5thPercentileSoldPrice": null,
                    "25thPercentileSoldPrice": null,
                    "75thPercentileSoldPrice": null,
                    "95thPercentileSoldPrice": null,
                    "medianSaleListingPrice": null,
                    "numberSaleListing": 5,
                    "highestSaleListingPrice": 1800000,
                    "lowestSaleListingPrice": 900000,
                    "auctionNumberAuctioned": 1,
                    "auctionNumberSold": null,
                    "auctionNumberWithdrawn": null,
                    "daysOnMarket": null,
                    "discountPercentage": null,
                    "medianRentListingPrice": null,
                    "numberRentListing": 3,
                    "highestRentListingPrice": 1500,
                    "lowestRentListingPrice": 450
                }
            },
            {
                "year": 2014,
                "month": 12,
                "values": {
                    "medianSoldPrice": null,
                    "numberSold": null,
                    "highestSoldPrice": null,
                    "lowestSoldPrice": null,
                    "5thPercentileSoldPrice": null,
                    "25thPercentileSoldPrice": null,
                    "75thPercentileSoldPrice": null,
                    "95thPercentileSoldPrice": null,
                    "medianSaleListingPrice": null,
                    "numberSaleListing": 3,
                    "highestSaleListingPrice": 1200000,
                    "lowestSaleListingPrice": 1100000,
                    "auctionNumberAuctioned": null,
                    "auctionNumberSold": null,
                    "auctionNumberWithdrawn": null,
                    "daysOnMarket": null,
                    "discountPercentage": null,
                    "medianRentListingPrice": null,
                    "numberRentListing": 3,
                    "highestRentListingPrice": 850,
                    "lowestRentListingPrice": 450
                }
            },
            {
                "year": 2015,
                "month": 3,
                "values": {
                    "medianSoldPrice": null,
                    "numberSold": null,
                    "highestSoldPrice": null,
                    "lowestSoldPrice": null,
                    "5thPercentileSoldPrice": null,
                    "25thPercentileSoldPrice": null,
                    "75thPercentileSoldPrice": null,
                    "95thPercentileSoldPrice": null,
                    "medianSaleListingPrice": null,
                    "numberSaleListing": 2,
                    "highestSaleListingPrice": 2800000,
                    "lowestSaleListingPrice": 1200000,
                    "auctionNumberAuctioned": null,
                    "auctionNumberSold": null,
                    "auctionNumberWithdrawn": null,
                    "daysOnMarket": null,
                    "discountPercentage": null,
                    "medianRentListingPrice": null,
                    "numberRentListing": 5,
                    "highestRentListingPrice": 980,
                    "lowestRentListingPrice": 400
                }
            },
            {
                "year": 2015,
                "month": 6,
                "values": {
                    "medianSoldPrice": null,
                    "numberSold": null,
                    "highestSoldPrice": null,
                    "lowestSoldPrice": null,
                    "5thPercentileSoldPrice": null,
                    "25thPercentileSoldPrice": null,
                    "75thPercentileSoldPrice": null,
                    "95thPercentileSoldPrice": null,
                    "medianSaleListingPrice": null,
                    "numberSaleListing": 2,
                    "highestSaleListingPrice": 2250000,
                    "lowestSaleListingPrice": 1200000,
                    "auctionNumberAuctioned": null,
                    "auctionNumberSold": null,
                    "auctionNumberWithdrawn": null,
                    "daysOnMarket": null,
                    "discountPercentage": null,
                    "medianRentListingPrice": null,
                    "numberRentListing": 3,
                    "highestRentListingPrice": 750,
                    "lowestRentListingPrice": 300
                }
            },
            {
                "year": 2015,
                "month": 9,
                "values": {
                    "medianSoldPrice": null,
                    "numberSold": 1,
                    "highestSoldPrice": 3500000,
                    "lowestSoldPrice": 3500000,
                    "5thPercentileSoldPrice": null,
                    "25thPercentileSoldPrice": null,
                    "75thPercentileSoldPrice": null,
                    "95thPercentileSoldPrice": null,
                    "medianSaleListingPrice": null,
                    "numberSaleListing": 3,
                    "highestSaleListingPrice": 3500000,
                    "lowestSaleListingPrice": 1500000,
                    "auctionNumberAuctioned": null,
                    "auctionNumberSold": null,
                    "auctionNumberWithdrawn": null,
                    "daysOnMarket": null,
                    "discountPercentage": null,
                    "medianRentListingPrice": null,
                    "numberRentListing": 3,
                    "highestRentListingPrice": 1700,
                    "lowestRentListingPrice": 350
                }
            },
            {
                "year": 2015,
                "month": 12,
                "values": {
                    "medianSoldPrice": null,
                    "numberSold": null,
                    "highestSoldPrice": null,
                    "lowestSoldPrice": null,
                    "5thPercentileSoldPrice": null,
                    "25thPercentileSoldPrice": null,
                    "75thPercentileSoldPrice": null,
                    "95thPercentileSoldPrice": null,
                    "medianSaleListingPrice": null,
                    "numberSaleListing": 1,
                    "highestSaleListingPrice": 1795000,
                    "lowestSaleListingPrice": 1795000,
                    "auctionNumberAuctioned": null,
                    "auctionNumberSold": null,
                    "auctionNumberWithdrawn": null,
                    "daysOnMarket": null,
                    "discountPercentage": null,
                    "medianRentListingPrice": null,
                    "numberRentListing": 6,
                    "highestRentListingPrice": 1700,
                    "lowestRentListingPrice": 450
                }
            },
            {
                "year": 2016,
                "month": 3,
                "values": {
                    "medianSoldPrice": null,
                    "numberSold": null,
                    "highestSoldPrice": null,
                    "lowestSoldPrice": null,
                    "5thPercentileSoldPrice": null,
                    "25thPercentileSoldPrice": null,
                    "75thPercentileSoldPrice": null,
                    "95thPercentileSoldPrice": null,
                    "medianSaleListingPrice": null,
                    "numberSaleListing": 1,
                    "highestSaleListingPrice": 1795000,
                    "lowestSaleListingPrice": 1795000,
                    "auctionNumberAuctioned": null,
                    "auctionNumberSold": null,
                    "auctionNumberWithdrawn": null,
                    "daysOnMarket": null,
                    "discountPercentage": null,
                    "medianRentListingPrice": null,
                    "numberRentListing": 4,
                    "highestRentListingPrice": 900,
                    "lowestRentListingPrice": 450
                }
            },
            {
                "year": 2016,
                "month": 6,
                "values": {
                    "medianSoldPrice": null,
                    "numberSold": null,
                    "highestSoldPrice": null,
                    "lowestSoldPrice": null,
                    "5thPercentileSoldPrice": null,
                    "25thPercentileSoldPrice": null,
                    "75thPercentileSoldPrice": null,
                    "95thPercentileSoldPrice": null,
                    "medianSaleListingPrice": null,
                    "numberSaleListing": 1,
                    "highestSaleListingPrice": 1795000,
                    "lowestSaleListingPrice": 1795000,
                    "auctionNumberAuctioned": null,
                    "auctionNumberSold": null,
                    "auctionNumberWithdrawn": null,
                    "daysOnMarket": null,
                    "discountPercentage": null,
                    "medianRentListingPrice": null,
                    "numberRentListing": 1,
                    "highestRentListingPrice": 700,
                    "lowestRentListingPrice": 700
                }
            },
            {
                "year": 2016,
                "month": 9,
                "values": {
                    "medianSoldPrice": null,
                    "numberSold": null,
                    "highestSoldPrice": null,
                    "lowestSoldPrice": null,
                    "5thPercentileSoldPrice": null,
                    "25thPercentileSoldPrice": null,
                    "75thPercentileSoldPrice": null,
                    "95thPercentileSoldPrice": null,
                    "medianSaleListingPrice": null,
                    "numberSaleListing": 1,
                    "highestSaleListingPrice": 1950000,
                    "lowestSaleListingPrice": 1950000,
                    "auctionNumberAuctioned": null,
                    "auctionNumberSold": null,
                    "auctionNumberWithdrawn": null,
                    "daysOnMarket": null,
                    "discountPercentage": null,
                    "medianRentListingPrice": null,
                    "numberRentListing": 2,
                    "highestRentListingPrice": 1700,
                    "lowestRentListingPrice": 850
                }
            },
            {
                "year": 2016,
                "month": 12,
                "values": {
                    "medianSoldPrice": null,
                    "numberSold": null,
                    "highestSoldPrice": null,
                    "lowestSoldPrice": null,
                    "5thPercentileSoldPrice": null,
                    "25thPercentileSoldPrice": null,
                    "75thPercentileSoldPrice": null,
                    "95thPercentileSoldPrice": null,
                    "medianSaleListingPrice": null,
                    "numberSaleListing": 1,
                    "highestSaleListingPrice": 1950000,
                    "lowestSaleListingPrice": 1950000,
                    "auctionNumberAuctioned": null,
                    "auctionNumberSold": null,
                    "auctionNumberWithdrawn": null,
                    "daysOnMarket": null,
                    "discountPercentage": null,
                    "medianRentListingPrice": null,
                    "numberRentListing": 3,
                    "highestRentListingPrice": 1700,
                    "lowestRentListingPrice": 435
                }
            },
            {
                "year": 2017,
                "month": 3,
                "values": {
                    "medianSoldPrice": null,
                    "numberSold": null,
                    "highestSoldPrice": null,
                    "lowestSoldPrice": null,
                    "5thPercentileSoldPrice": null,
                    "25thPercentileSoldPrice": null,
                    "75thPercentileSoldPrice": null,
                    "95thPercentileSoldPrice": null,
                    "medianSaleListingPrice": null,
                    "numberSaleListing": 1,
                    "highestSaleListingPrice": 1950000,
                    "lowestSaleListingPrice": 1950000,
                    "auctionNumberAuctioned": null,
                    "auctionNumberSold": null,
                    "auctionNumberWithdrawn": null,
                    "daysOnMarket": null,
                    "discountPercentage": null,
                    "medianRentListingPrice": null,
                    "numberRentListing": 4,
                    "highestRentListingPrice": 1700,
                    "lowestRentListingPrice": 530
                }
            },
            {
                "year": 2017,
                "month": 6,
                "values": {
                    "medianSoldPrice": null,
                    "numberSold": null,
                    "highestSoldPrice": null,
                    "lowestSoldPrice": null,
                    "5thPercentileSoldPrice": null,
                    "25thPercentileSoldPrice": null,
                    "75thPercentileSoldPrice": null,
                    "95thPercentileSoldPrice": null,
                    "medianSaleListingPrice": null,
                    "numberSaleListing": null,
                    "highestSaleListingPrice": null,
                    "lowestSaleListingPrice": null,
                    "auctionNumberAuctioned": null,
                    "auctionNumberSold": null,
                    "auctionNumberWithdrawn": null,
                    "daysOnMarket": null,
                    "discountPercentage": null,
                    "medianRentListingPrice": null,
                    "numberRentListing": 2,
                    "highestRentListingPrice": 1500,
                    "lowestRentListingPrice": 530
                }
            },
            {
                "year": 2017,
                "month": 9,
                "values": {
                    "medianSoldPrice": null,
                    "numberSold": null,
                    "highestSoldPrice": null,
                    "lowestSoldPrice": null,
                    "5thPercentileSoldPrice": null,
                    "25thPercentileSoldPrice": null,
                    "75thPercentileSoldPrice": null,
                    "95thPercentileSoldPrice": null,
                    "medianSaleListingPrice": null,
                    "numberSaleListing": null,
                    "highestSaleListingPrice": null,
                    "lowestSaleListingPrice": null,
                    "auctionNumberAuctioned": null,
                    "auctionNumberSold": null,
                    "auctionNumberWithdrawn": null,
                    "daysOnMarket": null,
                    "discountPercentage": null,
                    "medianRentListingPrice": null,
                    "numberRentListing": 5,
                    "highestRentListingPrice": 1500,
                    "lowestRentListingPrice": 360
                }
            },
            {
                "year": 2017,
                "month": 12,
                "values": {
                    "medianSoldPrice": null,
                    "numberSold": null,
                    "highestSoldPrice": null,
                    "lowestSoldPrice": null,
                    "5thPercentileSoldPrice": null,
                    "25thPercentileSoldPrice": null,
                    "75thPercentileSoldPrice": null,
                    "95thPercentileSoldPrice": null,
                    "medianSaleListingPrice": null,
                    "numberSaleListing": null,
                    "highestSaleListingPrice": null,
                    "lowestSaleListingPrice": null,
                    "auctionNumberAuctioned": null,
                    "auctionNumberSold": null,
                    "auctionNumberWithdrawn": null,
                    "daysOnMarket": null,
                    "discountPercentage": null,
                    "medianRentListingPrice": null,
                    "numberRentListing": 3,
                    "highestRentListingPrice": 750,
                    "lowestRentListingPrice": 355
                }
            },
            {
                "year": 2018,
                "month": 3,
                "values": {
                    "medianSoldPrice": null,
                    "numberSold": null,
                    "highestSoldPrice": null,
                    "lowestSoldPrice": null,
                    "5thPercentileSoldPrice": null,
                    "25thPercentileSoldPrice": null,
                    "75thPercentileSoldPrice": null,
                    "95thPercentileSoldPrice": null,
                    "medianSaleListingPrice": null,
                    "numberSaleListing": 2,
                    "highestSaleListingPrice": 3950000,
                    "lowestSaleListingPrice": 2900000,
                    "auctionNumberAuctioned": null,
                    "auctionNumberSold": null,
                    "auctionNumberWithdrawn": null,
                    "daysOnMarket": null,
                    "discountPercentage": null,
                    "medianRentListingPrice": null,
                    "numberRentListing": 3,
                    "highestRentListingPrice": 480,
                    "lowestRentListingPrice": 355
                }
            },
            {
                "year": 2018,
                "month": 6,
                "values": {
                    "medianSoldPrice": null,
                    "numberSold": null,
                    "highestSoldPrice": null,
                    "lowestSoldPrice": null,
                    "5thPercentileSoldPrice": null,
                    "25thPercentileSoldPrice": null,
                    "75thPercentileSoldPrice": null,
                    "95thPercentileSoldPrice": null,
                    "medianSaleListingPrice": null,
                    "numberSaleListing": 2,
                    "highestSaleListingPrice": 3400000,
                    "lowestSaleListingPrice": 2475000,
                    "auctionNumberAuctioned": null,
                    "auctionNumberSold": null,
                    "auctionNumberWithdrawn": null,
                    "daysOnMarket": null,
                    "discountPercentage": null,
                    "medianRentListingPrice": null,
                    "numberRentListing": 6,
                    "highestRentListingPrice": 750,
                    "lowestRentListingPrice": 390
                }
            },
            {
                "year": 2018,
                "month": 9,
                "values": {
                    "medianSoldPrice": null,
                    "numberSold": null,
                    "highestSoldPrice": null,
                    "lowestSoldPrice": null,
                    "5thPercentileSoldPrice": null,
                    "25thPercentileSoldPrice": null,
                    "75thPercentileSoldPrice": null,
                    "95thPercentileSoldPrice": null,
                    "medianSaleListingPrice": null,
                    "numberSaleListing": 2,
                    "highestSaleListingPrice": 3400000,
                    "lowestSaleListingPrice": 2475000,
                    "auctionNumberAuctioned": null,
                    "auctionNumberSold": null,
                    "auctionNumberWithdrawn": null,
                    "daysOnMarket": null,
                    "discountPercentage": null,
                    "medianRentListingPrice": null,
                    "numberRentListing": 7,
                    "highestRentListingPrice": 1500,
                    "lowestRentListingPrice": 390
                }
            },
            {
                "year": 2018,
                "month": 12,
                "values": {
                    "medianSoldPrice": null,
                    "numberSold": null,
                    "highestSoldPrice": null,
                    "lowestSoldPrice": null,
                    "5thPercentileSoldPrice": null,
                    "25thPercentileSoldPrice": null,
                    "75thPercentileSoldPrice": null,
                    "95thPercentileSoldPrice": null,
                    "medianSaleListingPrice": null,
                    "numberSaleListing": 1,
                    "highestSaleListingPrice": 3350000,
                    "lowestSaleListingPrice": 3350000,
                    "auctionNumberAuctioned": null,
                    "auctionNumberSold": null,
                    "auctionNumberWithdrawn": null,
                    "daysOnMarket": null,
                    "discountPercentage": null,
                    "medianRentListingPrice": null,
                    "numberRentListing": 1,
                    "highestRentListingPrice": 700,
                    "lowestRentListingPrice": 700
                }
            },
            {
                "year": 2019,
                "month": 3,
                "values": {
                    "medianSoldPrice": null,
                    "numberSold": null,
                    "highestSoldPrice": null,
                    "lowestSoldPrice": null,
                    "5thPercentileSoldPrice": null,
                    "25thPercentileSoldPrice": null,
                    "75thPercentileSoldPrice": null,
                    "95thPercentileSoldPrice": null,
                    "medianSaleListingPrice": null,
                    "numberSaleListing": 1,
                    "highestSaleListingPrice": 3350000,
                    "lowestSaleListingPrice": 3350000,
                    "auctionNumberAuctioned": null,
                    "auctionNumberSold": null,
                    "auctionNumberWithdrawn": null,
                    "daysOnMarket": null,
                    "discountPercentage": null,
                    "medianRentListingPrice": null,
                    "numberRentListing": 4,
                    "highestRentListingPrice": 985,
                    "lowestRentListingPrice": 400
                }
            },
            {
                "year": 2019,
                "month": 6,
                "values": {
                    "medianSoldPrice": null,
                    "numberSold": null,
                    "highestSoldPrice": null,
                    "lowestSoldPrice": null,
                    "5thPercentileSoldPrice": null,
                    "25thPercentileSoldPrice": null,
                    "75thPercentileSoldPrice": null,
                    "95thPercentileSoldPrice": null,
                    "medianSaleListingPrice": null,
                    "numberSaleListing": 1,
                    "highestSaleListingPrice": 436000,
                    "lowestSaleListingPrice": 436000,
                    "auctionNumberAuctioned": null,
                    "auctionNumberSold": null,
                    "auctionNumberWithdrawn": null,
                    "daysOnMarket": null,
                    "discountPercentage": null,
                    "medianRentListingPrice": null,
                    "numberRentListing": 1,
                    "highestRentListingPrice": 400,
                    "lowestRentListingPrice": 400
                }
            },
            {
                "year": 2019,
                "month": 9,
                "values": {
                    "medianSoldPrice": null,
                    "numberSold": null,
                    "highestSoldPrice": null,
                    "lowestSoldPrice": null,
                    "5thPercentileSoldPrice": null,
                    "25thPercentileSoldPrice": null,
                    "75thPercentileSoldPrice": null,
                    "95thPercentileSoldPrice": null,
                    "medianSaleListingPrice": null,
                    "numberSaleListing": null,
                    "highestSaleListingPrice": null,
                    "lowestSaleListingPrice": null,
                    "auctionNumberAuctioned": null,
                    "auctionNumberSold": null,
                    "auctionNumberWithdrawn": null,
                    "daysOnMarket": null,
                    "discountPercentage": null,
                    "medianRentListingPrice": null,
                    "numberRentListing": 4,
                    "highestRentListingPrice": 950,
                    "lowestRentListingPrice": 395
                }
            },
            {
                "year": 2019,
                "month": 12,
                "values": {
                    "medianSoldPrice": null,
                    "numberSold": null,
                    "highestSoldPrice": null,
                    "lowestSoldPrice": null,
                    "5thPercentileSoldPrice": null,
                    "25thPercentileSoldPrice": null,
                    "75thPercentileSoldPrice": null,
                    "95thPercentileSoldPrice": null,
                    "medianSaleListingPrice": null,
                    "numberSaleListing": 1,
                    "highestSaleListingPrice": 1910000,
                    "lowestSaleListingPrice": 1910000,
                    "auctionNumberAuctioned": 1,
                    "auctionNumberSold": null,
                    "auctionNumberWithdrawn": null,
                    "daysOnMarket": null,
                    "discountPercentage": null,
                    "medianRentListingPrice": null,
                    "numberRentListing": 5,
                    "highestRentListingPrice": 1500,
                    "lowestRentListingPrice": 395
                }
            },
            {
                "year": 2020,
                "month": 3,
                "values": {
                    "medianSoldPrice": null,
                    "numberSold": null,
                    "highestSoldPrice": null,
                    "lowestSoldPrice": null,
                    "5thPercentileSoldPrice": null,
                    "25thPercentileSoldPrice": null,
                    "75thPercentileSoldPrice": null,
                    "95thPercentileSoldPrice": null,
                    "medianSaleListingPrice": null,
                    "numberSaleListing": 3,
                    "highestSaleListingPrice": 2500000,
                    "lowestSaleListingPrice": 1910000,
                    "auctionNumberAuctioned": 1,
                    "auctionNumberSold": null,
                    "auctionNumberWithdrawn": null,
                    "daysOnMarket": null,
                    "discountPercentage": null,
                    "medianRentListingPrice": null,
                    "numberRentListing": 3,
                    "highestRentListingPrice": 1500,
                    "lowestRentListingPrice": 400
                }
            },
            {
                "year": 2020,
                "month": 6,
                "values": {
                    "medianSoldPrice": null,
                    "numberSold": null,
                    "highestSoldPrice": null,
                    "lowestSoldPrice": null,
                    "5thPercentileSoldPrice": null,
                    "25thPercentileSoldPrice": null,
                    "75thPercentileSoldPrice": null,
                    "95thPercentileSoldPrice": null,
                    "medianSaleListingPrice": null,
                    "numberSaleListing": 3,
                    "highestSaleListingPrice": 2500000,
                    "lowestSaleListingPrice": 1890000,
                    "auctionNumberAuctioned": null,
                    "auctionNumberSold": null,
                    "auctionNumberWithdrawn": null,
                    "daysOnMarket": null,
                    "discountPercentage": null,
                    "medianRentListingPrice": null,
                    "numberRentListing": 9,
                    "highestRentListingPrice": 1200,
                    "lowestRentListingPrice": 400
                }
            },
            {
                "year": 2020,
                "month": 9,
                "values": {
                    "medianSoldPrice": null,
                    "numberSold": null,
                    "highestSoldPrice": null,
                    "lowestSoldPrice": null,
                    "5thPercentileSoldPrice": null,
                    "25thPercentileSoldPrice": null,
                    "75thPercentileSoldPrice": null,
                    "95thPercentileSoldPrice": null,
                    "medianSaleListingPrice": null,
                    "numberSaleListing": 2,
                    "highestSaleListingPrice": 1899000,
                    "lowestSaleListingPrice": 1890000,
                    "auctionNumberAuctioned": null,
                    "auctionNumberSold": null,
                    "auctionNumberWithdrawn": null,
                    "daysOnMarket": null,
                    "discountPercentage": null,
                    "medianRentListingPrice": null,
                    "numberRentListing": 5,
                    "highestRentListingPrice": 1500,
                    "lowestRentListingPrice": 400
                }
            },
            {
                "year": 2020,
                "month": 12,
                "values": {
                    "medianSoldPrice": null,
                    "numberSold": null,
                    "highestSoldPrice": null,
                    "lowestSoldPrice": null,
                    "5thPercentileSoldPrice": null,
                    "25thPercentileSoldPrice": null,
                    "75thPercentileSoldPrice": null,
                    "95thPercentileSoldPrice": null,
                    "medianSaleListingPrice": null,
                    "numberSaleListing": 2,
                    "highestSaleListingPrice": 6950000,
                    "lowestSaleListingPrice": 6950000,
                    "auctionNumberAuctioned": null,
                    "auctionNumberSold": null,
                    "auctionNumberWithdrawn": null,
                    "daysOnMarket": null,
                    "discountPercentage": null,
                    "medianRentListingPrice": null,
                    "numberRentListing": 3,
                    "highestRentListingPrice": 1500,
                    "lowestRentListingPrice": 500
                }
            },
            {
                "year": 2021,
                "month": 3,
                "values": {
                    "medianSoldPrice": null,
                    "numberSold": null,
                    "highestSoldPrice": null,
                    "lowestSoldPrice": null,
                    "5thPercentileSoldPrice": null,
                    "25thPercentileSoldPrice": null,
                    "75thPercentileSoldPrice": null,
                    "95thPercentileSoldPrice": null,
                    "medianSaleListingPrice": null,
                    "numberSaleListing": 2,
                    "highestSaleListingPrice": 6484000,
                    "lowestSaleListingPrice": 3900000,
                    "auctionNumberAuctioned": null,
                    "auctionNumberSold": null,
                    "auctionNumberWithdrawn": null,
                    "daysOnMarket": null,
                    "discountPercentage": null,
                    "medianRentListingPrice": null,
                    "numberRentListing": 2,
                    "highestRentListingPrice": 1050,
                    "lowestRentListingPrice": 600
                }
            },
            {
                "year": 2021,
                "month": 6,
                "values": {
                    "medianSoldPrice": null,
                    "numberSold": 3,
                    "highestSoldPrice": 6325000,
                    "lowestSoldPrice": 2705000,
                    "5thPercentileSoldPrice": null,
                    "25thPercentileSoldPrice": null,
                    "75thPercentileSoldPrice": null,
                    "95thPercentileSoldPrice": null,
                    "medianSaleListingPrice": null,
                    "numberSaleListing": 7,
                    "highestSaleListingPrice": 6484000,
                    "lowestSaleListingPrice": 2400000,
                    "auctionNumberAuctioned": 4,
                    "auctionNumberSold": 2,
                    "auctionNumberWithdrawn": null,
                    "daysOnMarket": null,
                    "discountPercentage": null,
                    "medianRentListingPrice": null,
                    "numberRentListing": 2,
                    "highestRentListingPrice": 800,
                    "lowestRentListingPrice": 600
                }
            }
        ]
    }
}